mlflow_pipelines/__init__.py
mlflow_pipelines/main.py
mlflow_pipelines/fetch_data/__init__.py
mlflow_pipelines/fetch_data/get_data.py
mlflow_pipelines/train_model/__init__.py
mlflow_pipelines/train_model/model_train.py
mlflow_pipelines/upload_data/__init__.py
mlflow_pipelines/upload_data/data_upload.py
pp_project_pkg/__init__.py
pp_project_pkg/extra.py
pp_project_pkg/newsvendor.py
pp_project_pkg/pp_tables.py
pp_project_pkg/train_loop.py
pp_project_pkg/utils.py
pp_project_pkg/version.py
pp_project_pkg/wrangling.py
pp_project_pkg-1.0.202310162036.data/scripts/pp_project_run.py
pp_project_pkg-1.0.202310162036.dist-info/METADATA
pp_project_pkg-1.0.202310162036.dist-info/WHEEL
pp_project_pkg-1.0.202310162036.dist-info/top_level.txt
pp_project_pkg-1.0.202310162036.dist-info/RECORD
