Metadata-Version: 2.1
Name: pp-project-pkg
Version: 1.0.202310162036
Summary: Production Planing functions package
Author: ['Malav Bateriwala']
Requires-Python: >=3.8
Requires-Dist: mb-base
